mina_backend/__init__.py
mina_backend/hooks.py
mina_build-0.6.1.dist-info/METADATA
mina_build-0.6.1.dist-info/WHEEL
mina_build-0.6.1.dist-info/entry_points.txt
mina_build-0.6.1.dist-info/RECORD
