Metadata-Version: 2.1
Name: mina-build
Version: 0.6.1
Summary: build backend for Mina Package Structure
Author-Email: GreyElaina <GreyElaina@outlook.com>
License: MIT
Requires-Python: >=3.9
Requires-Dist: pdm-backend
